[
      {
        "name": "Auto Map Switch",
        "type": "toggle",
        "img": "images/settings/tab_switching_on.png",
        "disabled_img": "images/settings/tab_switching_off.png",
        "codes": "tab_switch"
      },
      {
        "name": "Show All Locations",
        "type": "toggle",
        "img": "images/settings/visibility_checks_on.png",
        "disabled_img": "images/settings/visibility_checks_off.png",
        "codes": "visibility_markers"
      },
      {
        "name": "Current Level",
        "type": "progressive",
        "codes": "cur_level_id"
      }
]